pyvmodule/__init__.py
pyvmodule/ast.py
pyvmodule/ctrlblk.py
pyvmodule/develope.py
pyvmodule/expr.py
pyvmodule/naming.py
pyvmodule/vcircuit.py
pyvmodule/vfunction.py
pyvmodule/viterator.py
pyvmodule/vmodule.py
pyvmodule/vstruct.py
pyvmodule/wire.py
pyvmodule/compute/__init__.py
pyvmodule/compute/auto_connect.py
pyvmodule/compute/copy.py
pyvmodule/compute/driver.py
pyvmodule/compute/exceptions.py
pyvmodule/compute/value.py
pyvmodule/compute/width.py
pyvmodule/language/__init__.py
pyvmodule/language/code_align.py
pyvmodule/language/verilog.py
pyvmodule/tools/__init__.py
pyvmodule/tools/bitutil.py
pyvmodule/tools/encodings.py
pyvmodule/tools/logic.py
pyvmodule/tools/memorization.py
pyvmodule/tools/pipeline.py
pyvmodule/tools/polynomial.py
pyvmodule/tools/sigext.py
pyvmodule/tools/utility.py
pyvmodule/tools/bitdoc/__init__.py
pyvmodule/tools/bitdoc/bitdoc.py
pyvmodule/tools/bitdoc/csrdoc.py
pyvmodule/tools/bitdoc/instdoc.py
pyvmodule/tools/bitdoc/pipedoc.py
pyvmodule/tools/hash/__init__.py
pyvmodule/tools/hash/functions.py
pyvmodule/tools/hash/matrix.py
pyvmodule/tools/hash/seeds.py
pyvmodule/tools/modules/__init__.py
pyvmodule/tools/modules/carry.py
pyvmodule/tools/modules/clock_gating.py
pyvmodule/tools/modules/dividor.py
pyvmodule/tools/modules/dividor64.py
pyvmodule/tools/modules/event_counter.py
pyvmodule/tools/modules/fifo.py
pyvmodule/tools/modules/multiplier.py
pyvmodule/tools/modules/raminit.py
pyvmodule/tools/modules/amba/__init__.py
pyvmodule/tools/modules/amba/axi/__init__.py
pyvmodule/tools/modules/amba/axi/axi.py
pyvmodule/tools/modules/amba/axi/axi2ram.py
pyvmodule/tools/modules/amba/axi/axi_ram.py
pyvmodule/tools/modules/amba/axi/bridge.py
pyvmodule/tools/modules/amba/axi/common.py
pyvmodule/tools/modules/amba/axi/delay.py
pyvmodule/tools/modules/sram/__init__.py
pyvmodule/tools/modules/sram/dual.py
pyvmodule/tools/modules/sram/lite.py
pyvmodule-2.0.16.dist-info/LICENSE
pyvmodule-2.0.16.dist-info/METADATA
pyvmodule-2.0.16.dist-info/WHEEL
pyvmodule-2.0.16.dist-info/top_level.txt
pyvmodule-2.0.16.dist-info/RECORD
