Metadata-Version: 2.1
Name: pyvmodule
Version: 2.0.16
Summary: pyvmodule:an advanded verilog coding toolkit
Home-page: https://gitee.com/tanhongze/pyvmodule.git
Author: H.Z.Tan
Author-email: tanhongze@loongson.cn
License: UNKNOWN
Platform: UNKNOWN
Classifier: Programming Language :: Python :: 3
Classifier: License :: OSI Approved :: MIT License
Classifier: Operating System :: OS Independent
Requires-Python: >=3.6
Requires-Dist: xlrd
